envseal/__init__.py
envseal/changes.py
envseal/cli.py
envseal/config.py
envseal/crypto.py
envseal/diffing.py
envseal/dotenvio.py
envseal/interactive.py
envseal/scanner.py
envseal/sops.py
envseal/vault.py
envseal_vault-0.2.0.dist-info/METADATA
envseal_vault-0.2.0.dist-info/WHEEL
envseal_vault-0.2.0.dist-info/entry_points.txt
envseal_vault-0.2.0.dist-info/licenses/LICENSE
envseal_vault-0.2.0.dist-info/RECORD
