Metadata-Version: 2.4
Name: envseal-vault
Version: 0.2.0
Summary: Secure, centralized environment variable management for AI coding era - SOPS + age encryption for multi-project .env files
Project-URL: Homepage, https://github.com/chicogong/envseal
Project-URL: Repository, https://github.com/chicogong/envseal
Project-URL: Issues, https://github.com/chicogong/envseal/issues
Project-URL: Documentation, https://github.com/chicogong/envseal/blob/master/README.md
Author: chicogong
Maintainer: chicogong
License: Apache-2.0
License-File: LICENSE
Keywords: age,ai-coding,claude-code,cursor,dotenv,encryption,env,environment,multi-project,secret-management,secrets,sops,vault,vibe-coding
Classifier: Development Status :: 4 - Beta
Classifier: Intended Audience :: Developers
Classifier: License :: OSI Approved :: Apache Software License
Classifier: Operating System :: OS Independent
Classifier: Programming Language :: Python :: 3
Classifier: Programming Language :: Python :: 3.9
Classifier: Programming Language :: Python :: 3.10
Classifier: Programming Language :: Python :: 3.11
Classifier: Programming Language :: Python :: 3.12
Classifier: Topic :: Security :: Cryptography
Classifier: Topic :: Software Development :: Libraries :: Python Modules
Classifier: Topic :: System :: Systems Administration
Requires-Python: >=3.9
Requires-Dist: python-dotenv>=1.0.0
Requires-Dist: pyyaml>=6.0
Requires-Dist: typer[all]>=0.9.0
Provides-Extra: dev
Requires-Dist: mypy>=1.7.0; extra == 'dev'
Requires-Dist: pytest-cov>=4.0.0; extra == 'dev'
Requires-Dist: pytest>=7.0.0; extra == 'dev'
Requires-Dist: ruff>=0.1.0; extra == 'dev'
Requires-Dist: types-pyyaml>=6.0.0; extra == 'dev'
